mobilitypy/__init__.py
mobilitypy/_version.py
mobilitypy/mobility.py
mobilitypy/src/__init__.py
mobilitypy/src/_alloy_params.py
mobilitypy/src/_constants.py
mobilitypy/src/_mobilities_2d_carrier.py
mobilitypy/src/_mobilities_3d_carrier.py
mobilitypy/src/_mobility_carrier_general.py
mobilitypy/src/database.py
mobilitypy/utilities/__init__.py
mobilitypy/utilities/_general_plot_functions.py
mobilitypy/utilities/_plot_fns.py
mobilitypy/utilities/_quasi3d_plot_fns.py
mobilitypy-1.0.2.dist-info/licenses/LICENSE
mobilitypy-1.0.2.dist-info/METADATA
mobilitypy-1.0.2.dist-info/WHEEL
mobilitypy-1.0.2.dist-info/top_level.txt
mobilitypy-1.0.2.dist-info/RECORD
