Metadata-Version: 2.4
Name: mobilitypy
Version: 1.0.2
Summary: mobilitypy: Python package for mobility calculations in semiconductors
Author-email: Badal Mondal <badalmondal.chembgc@gmail.com>
Maintainer-email: Badal Mondal <badalmondal.chembgc@gmail.com>
License-Expression: GPL-3.0-only
Project-URL: Homepage, https://github.com/SemiconductorTransport/mobilitypy/wiki
Project-URL: Documentation, https://github.com/SemiconductorTransport/mobilitypy/wiki/Package-Documentation
Project-URL: Repository, https://github.com/SemiconductorTransport/mobilitypy.git
Project-URL: Issues, https://github.com/SemiconductorTransport/mobilitypy/issues
Project-URL: Changelog, https://github.com/SemiconductorTransport/mobilitypy/wiki/Brief-release-history
Project-URL: Releasenotes, https://github.com/SemiconductorTransport/mobilitypy/releases
Keywords: mobility,Electron gas,2DEG,3DEG,Alloy disorder
Classifier: Development Status :: 5 - Production/Stable
Classifier: Programming Language :: Python :: 3
Classifier: Operating System :: OS Independent
Requires-Python: >=3.12
License-File: LICENSE
Requires-Dist: numpy
Requires-Dist: scipy
Requires-Dist: matplotlib
Requires-Dist: pandas
Provides-Extra: test
Requires-Dist: pytest>=7.0; extra == "test"
Requires-Dist: pytest-cov>=4.1; extra == "test"
Dynamic: license-file
